[{"day":"Monday","weather":"rainy","season":"fall","time":"day","area":"manhattan","avgDuration":807.8155583194061,"avgDistance":2.469631155505461,"avgFareAmount":11.456062355059789,"avgTipAmount":2.3295687097568245,"avgTotalAmount":17.767592794123363,"numberOfTrips":154374},{"day":"Monday","weather":"rainy","season":"fall","time":"day","area":"not manhattan","avgDuration":1973.9799797854143,"avgDistance":10.540003887420308,"avgFareAmount":33.17986316280516,"avgTipAmount":5.83191299953351,"avgTotalAmount":45.84066630384077,"numberOfTrips":25724},{"day":"Monday","weather":"rainy","season":"fall","time":"night","area":"manhattan","avgDuration":724.5222315757251,"avgDistance":2.912703757557205,"avgFareAmount":11.791666488099795,"avgTipAmount":2.3681804545802403,"avgTotalAmount":18.117060993342005,"numberOfTrips":65335},{"day":"Monday","weather":"rainy","season":"fall","time":"night","area":"not manhattan","avgDuration":1412.6953155680224,"avgDistance":11.502112201963534,"avgFareAmount":34.153008134642356,"avgTipAmount":5.854162692847125,"avgTotalAmount":46.00919438990182,"numberOfTrips":17825},{"day":"Monday","weather":"rainy","season":"spring","time":"day","area":"manhattan","avgDuration":781.0922791522335,"avgDistance":2.426050350499893,"avgFareAmount":11.201857649434439,"avgTipAmount":2.2380468865431022,"avgTotalAmount":17.413618767750727,"numberOfTrips":121826},{"day":"Monday","weather":"rainy","season":"spring","time":"day","area":"not manhattan","avgDuration":1783.4460622807949,"avgDistance":9.960625464980337,"avgFareAmount":31.31445158890424,"avgTipAmount":5.619327771282814,"avgTotalAmount":43.80049686470401,"numberOfTrips":18818},{"day":"Monday","weather":"rainy","season":"spring","time":"night","area":"manhattan","avgDuration":662.5735892014961,"avgDistance":2.6895047975280533,"avgFareAmount":10.9630663522524,"avgTipAmount":2.2513908765652952,"avgTotalAmount":17.08843145226866,"numberOfTrips":24596},{"day":"Monday","weather":"rainy","season":"spring","time":"night","area":"not manhattan","avgDuration":1320.1251680107528,"avgDistance":10.78853998655914,"avgFareAmount":31.939129704301077,"avgTipAmount":5.765068884408603,"avgTotalAmount":43.60866095430107,"numberOfTrips":5952},{"day":"Monday","weather":"rainy","season":"summer","time":"day","area":"manhattan","avgDuration":807.6203869562029,"avgDistance":2.50525559640908,"avgFareAmount":11.52059426165111,"avgTipAmount":2.1874902841938764,"avgTotalAmount":17.520881126719253,"numberOfTrips":190926},{"day":"Monday","weather":"rainy","season":"summer","time":"day","area":"not manhattan","avgDuration":1883.1757680250785,"avgDistance":10.229126645768025,"avgFareAmount":32.29180125391849,"avgTipAmount":5.362225391849529,"avgTotalAmount":44.230868652037614,"numberOfTrips":31900},{"day":"Monday","weather":"rainy","season":"summer","time":"night","area":"manhattan","avgDuration":704.2627716423227,"avgDistance":3.207850374064838,"avgFareAmount":12.359550409690062,"avgTipAmount":2.3134442465265406,"avgTotalAmount":18.686128250801566,"numberOfTrips":14035},{"day":"Monday","weather":"rainy","season":"summer","time":"night","area":"not manhattan","avgDuration":1369.4355841371919,"avgDistance":11.722070739549839,"avgFareAmount":34.683142550911036,"avgTipAmount":5.753121114683816,"avgTotalAmount":46.24685316184352,"numberOfTrips":4665},{"day":"Monday","weather":"rainy","season":"winter","time":"day","area":"manhattan","avgDuration":685.5008222275515,"avgDistance":2.201743036760423,"avgFareAmount":10.2432209907842,"avgTipAmount":2.022215389359005,"avgTotalAmount":15.882106872451951,"numberOfTrips":116756},{"day":"Monday","weather":"rainy","season":"winter","time":"day","area":"not manhattan","avgDuration":1545.8570640852836,"avgDistance":9.79586263938243,"avgFareAmount":30.260390883470162,"avgTipAmount":4.999807008944982,"avgTotalAmount":41.28966486950129,"numberOfTrips":16322},{"day":"Monday","weather":"rainy","season":"winter","time":"night","area":"manhattan","avgDuration":635.2442212795429,"avgDistance":2.854585750151502,"avgFareAmount":11.193510518569822,"avgTipAmount":2.1930932386806337,"avgTotalAmount":17.269847632239635,"numberOfTrips":11551},{"day":"Monday","weather":"rainy","season":"winter","time":"night","area":"not manhattan","avgDuration":1352.1874799357945,"avgDistance":11.583255216693418,"avgFareAmount":33.90887961476726,"avgTipAmount":5.70391974317817,"avgTotalAmount":45.23805136436597,"numberOfTrips":3115},{"day":"Monday","weather":"sunny","season":"fall","time":"day","area":"manhattan","avgDuration":840.6064232095816,"avgDistance":2.5048876783628247,"avgFareAmount":11.82566943307748,"avgTipAmount":2.323441278322915,"avgTotalAmount":18.003588929552834,"numberOfTrips":721633},{"day":"Monday","weather":"sunny","season":"fall","time":"day","area":"not manhattan","avgDuration":1887.805444748271,"avgDistance":10.33236158919093,"avgFareAmount":32.763753257198005,"avgTipAmount":5.806177014637285,"avgTotalAmount":45.40098552356442,"numberOfTrips":124340},{"day":"Monday","weather":"sunny","season":"fall","time":"night","area":"manhattan","avgDuration":706.9072522216705,"avgDistance":3.0076336295560715,"avgFareAmount":11.925557773566934,"avgTipAmount":2.3792886601072074,"avgTotalAmount":18.28445691935108,"numberOfTrips":98687},{"day":"Monday","weather":"sunny","season":"fall","time":"night","area":"not manhattan","avgDuration":1347.207329162821,"avgDistance":11.503901138344785,"avgFareAmount":33.991153385977505,"avgTipAmount":5.962946364475439,"avgTotalAmount":45.934099750452944,"numberOfTrips":29253},{"day":"Monday","weather":"sunny","season":"spring","time":"day","area":"manhattan","avgDuration":773.576409837032,"avgDistance":2.4621000711174212,"avgFareAmount":11.288599300365119,"avgTipAmount":2.21412715594282,"avgTotalAmount":17.32874891034815,"numberOfTrips":797273},{"day":"Monday","weather":"sunny","season":"spring","time":"day","area":"not manhattan","avgDuration":1834.3605748829016,"avgDistance":10.15972881220225,"avgFareAmount":31.90260594899716,"avgTipAmount":5.606617718883863,"avgTotalAmount":44.24015212778734,"numberOfTrips":124895},{"day":"Monday","weather":"sunny","season":"spring","time":"night","area":"manhattan","avgDuration":675.1362756484708,"avgDistance":2.9996658850685542,"avgFareAmount":11.71438140526958,"avgTipAmount":2.307638258862373,"avgTotalAmount":17.96867274413984,"numberOfTrips":136899},{"day":"Monday","weather":"sunny","season":"spring","time":"night","area":"not manhattan","avgDuration":1357.0445179148085,"avgDistance":11.595884976164847,"avgFareAmount":34.1698821056948,"avgTipAmount":5.91237890204521,"avgTotalAmount":45.94314290840125,"numberOfTrips":39018},{"day":"Monday","weather":"sunny","season":"summer","time":"day","area":"manhattan","avgDuration":756.3223475186477,"avgDistance":2.5072385772406496,"avgFareAmount":11.250584355381314,"avgTipAmount":2.199330130717223,"avgTotalAmount":17.336577402702225,"numberOfTrips":641767},{"day":"Monday","weather":"sunny","season":"summer","time":"day","area":"not manhattan","avgDuration":1784.2389307452495,"avgDistance":10.30423109040974,"avgFareAmount":32.10944143408551,"avgTipAmount":5.463499665973872,"avgTotalAmount":44.28866807081354,"numberOfTrips":107776},{"day":"Monday","weather":"sunny","season":"summer","time":"night","area":"manhattan","avgDuration":697.519348941997,"avgDistance":2.9161713580346844,"avgFareAmount":11.673188443922808,"avgTipAmount":2.27625891225017,"avgTotalAmount":17.880043170029207,"numberOfTrips":148251},{"day":"Monday","weather":"sunny","season":"summer","time":"night","area":"not manhattan","avgDuration":1440.1048253336396,"avgDistance":11.613444333869198,"avgFareAmount":34.50074459669805,"avgTipAmount":5.7117339049222995,"avgTotalAmount":46.06144020005614,"numberOfTrips":39189},{"day":"Monday","weather":"sunny","season":"winter","time":"day","area":"manhattan","avgDuration":764.5339692264041,"avgDistance":2.326442492403592,"avgFareAmount":11.608941439256963,"avgTipAmount":2.2790357085469184,"avgTotalAmount":17.841000843964927,"numberOfTrips":690787},{"day":"Monday","weather":"sunny","season":"winter","time":"day","area":"not manhattan","avgDuration":1704.959427830864,"avgDistance":9.810326124801733,"avgFareAmount":33.02313899957445,"avgTipAmount":5.574486730627878,"avgTotalAmount":45.47302680954776,"numberOfTrips":103396},{"day":"Monday","weather":"sunny","season":"winter","time":"night","area":"manhattan","avgDuration":664.4418091839483,"avgDistance":2.811874831672502,"avgFareAmount":11.984707867627256,"avgTipAmount":2.35376085712362,"avgTotalAmount":18.454762069081607,"numberOfTrips":118816},{"day":"Monday","weather":"sunny","season":"winter","time":"night","area":"not manhattan","avgDuration":1291.45959142104,"avgDistance":11.219145099448838,"avgFareAmount":35.03998652048885,"avgTipAmount":5.786910795590702,"avgTotalAmount":46.95587886412653,"numberOfTrips":33384},{"day":"Tuesday","weather":"rainy","season":"fall","time":"day","area":"manhattan","avgDuration":910.2228231659419,"avgDistance":2.337681301045241,"avgFareAmount":11.939162604345587,"avgTipAmount":2.374483299068266,"avgTotalAmount":18.1085815765439,"numberOfTrips":266063},{"day":"Tuesday","weather":"rainy","season":"fall","time":"day","area":"not manhattan","avgDuration":2100.344332742994,"avgDistance":9.657213772267944,"avgFareAmount":31.778198510261486,"avgTipAmount":5.426271747056985,"avgTotalAmount":43.713045629753104,"numberOfTrips":38396},{"day":"Tuesday","weather":"rainy","season":"fall","time":"night","area":"manhattan","avgDuration":740.6795110406471,"avgDistance":3.0355279060683347,"avgFareAmount":12.137443533007055,"avgTipAmount":2.4600599710484596,"avgTotalAmount":18.584968865605113,"numberOfTrips":43521},{"day":"Tuesday","weather":"rainy","season":"fall","time":"night","area":"not manhattan","avgDuration":1416.416459998163,"avgDistance":11.36457518140902,"avgFareAmount":33.88078350326077,"avgTipAmount":5.6513603380178195,"avgTotalAmount":45.34607329842932,"numberOfTrips":10887},{"day":"Tuesday","weather":"rainy","season":"spring","time":"day","area":"manhattan","avgDuration":824.6219770701798,"avgDistance":2.3367114170446515,"avgFareAmount":11.363237982358172,"avgTipAmount":2.291934333188977,"avgTotalAmount":17.474172269961024,"numberOfTrips":87746},{"day":"Tuesday","weather":"rainy","season":"spring","time":"day","area":"not manhattan","avgDuration":1726.1972733912196,"avgDistance":9.325699910736022,"avgFareAmount":29.711315426438365,"avgTipAmount":5.031175850036517,"avgTotalAmount":41.082951391706565,"numberOfTrips":12323},{"day":"Tuesday","weather":"rainy","season":"spring","time":"night","area":"manhattan","avgDuration":688.6502036485608,"avgDistance":2.7401115788753123,"avgFareAmount":11.161734264298182,"avgTipAmount":2.350476434952254,"avgTotalAmount":17.39196221377965,"numberOfTrips":29217},{"day":"Tuesday","weather":"rainy","season":"spring","time":"night","area":"not manhattan","avgDuration":1343.8211482222564,"avgDistance":10.492768970293982,"avgFareAmount":31.39871633061413,"avgTipAmount":5.405140834231183,"avgTotalAmount":42.53048176081268,"numberOfTrips":6497},{"day":"Tuesday","weather":"rainy","season":"summer","time":"day","area":"manhattan","avgDuration":804.48131772551,"avgDistance":2.3688086652411844,"avgFareAmount":11.228574729097959,"avgTipAmount":2.2455102743449427,"avgTotalAmount":17.57019171529011,"numberOfTrips":110372},{"day":"Tuesday","weather":"rainy","season":"summer","time":"day","area":"not manhattan","avgDuration":1722.400418434358,"avgDistance":9.695172313593304,"avgFareAmount":30.49890567792178,"avgTipAmount":5.102127041320393,"avgTotalAmount":42.402413552623926,"numberOfTrips":17207},{"day":"Tuesday","weather":"rainy","season":"summer","time":"night","area":"manhattan","avgDuration":710.012347130762,"avgDistance":2.773823788805268,"avgFareAmount":11.372102539981185,"avgTipAmount":2.3179571378174977,"avgTotalAmount":17.575802269520224,"numberOfTrips":34016},{"day":"Tuesday","weather":"rainy","season":"summer","time":"night","area":"not manhattan","avgDuration":1423.6889337929395,"avgDistance":10.960771425175324,"avgFareAmount":32.61807440865327,"avgTipAmount":5.289605372637585,"avgTotalAmount":43.5753025080233,"numberOfTrips":8413},{"day":"Tuesday","weather":"rainy","season":"winter","time":"day","area":"manhattan","avgDuration":940.8864423552697,"avgDistance":2.2395947980982296,"avgFareAmount":11.920187595465007,"avgTipAmount":2.446854226276273,"avgTotalAmount":18.389258761267563,"numberOfTrips":92966},{"day":"Tuesday","weather":"rainy","season":"winter","time":"day","area":"not manhattan","avgDuration":2007.2486018939676,"avgDistance":9.508377451345911,"avgFareAmount":31.213779733054956,"avgTipAmount":5.637760793378569,"avgTotalAmount":43.884376258295426,"numberOfTrips":13411},{"day":"Tuesday","weather":"rainy","season":"winter","time":"night","area":"manhattan","avgDuration":740.0714967426035,"avgDistance":2.7169986306485745,"avgFareAmount":11.439351425370347,"avgTipAmount":2.423656168305739,"avgTotalAmount":17.7465981990954,"numberOfTrips":24099},{"day":"Tuesday","weather":"rainy","season":"winter","time":"night","area":"not manhattan","avgDuration":1356.9464594127808,"avgDistance":10.266160046056418,"avgFareAmount":30.880592976396084,"avgTipAmount":5.557060065246594,"avgTotalAmount":42.207883323738244,"numberOfTrips":5211},{"day":"Tuesday","weather":"sunny","season":"fall","time":"day","area":"manhattan","avgDuration":905.1480004801,"avgDistance":2.382991878308448,"avgFareAmount":12.03231497870591,"avgTipAmount":2.4213158464728517,"avgTotalAmount":18.29976254364702,"numberOfTrips":724849},{"day":"Tuesday","weather":"sunny","season":"fall","time":"day","area":"not manhattan","avgDuration":1923.9907082050354,"avgDistance":9.721544647708749,"avgFareAmount":31.557146259735553,"avgTipAmount":5.57150217351929,"avgTotalAmount":43.910692628147075,"numberOfTrips":110420},{"day":"Tuesday","weather":"sunny","season":"fall","time":"night","area":"manhattan","avgDuration":733.5893400469362,"avgDistance":2.8645557193191094,"avgFareAmount":11.729727871361971,"avgTipAmount":2.4742292535123065,"avgTotalAmount":18.128399552145336,"numberOfTrips":158087},{"day":"Tuesday","weather":"sunny","season":"fall","time":"night","area":"not manhattan","avgDuration":1321.1721616077534,"avgDistance":10.484144543211345,"avgFareAmount":31.459060855605433,"avgTipAmount":5.426041561375866,"avgTotalAmount":42.692008799833516,"numberOfTrips":33637},{"day":"Tuesday","weather":"sunny","season":"spring","time":"day","area":"manhattan","avgDuration":854.9843146122269,"avgDistance":2.3620968124953285,"avgFareAmount":11.620231538992082,"avgTipAmount":2.32378240273385,"avgTotalAmount":17.760321995589283,"numberOfTrips":1056971},{"day":"Tuesday","weather":"sunny","season":"spring","time":"day","area":"not manhattan","avgDuration":1885.562626129531,"avgDistance":9.35783254852736,"avgFareAmount":30.404727906960616,"avgTipAmount":5.228046838699835,"avgTotalAmount":42.198880836633215,"numberOfTrips":144197},{"day":"Tuesday","weather":"sunny","season":"spring","time":"night","area":"manhattan","avgDuration":705.5124122053796,"avgDistance":2.9096322329209228,"avgFareAmount":11.659136542234464,"avgTipAmount":2.394977536274265,"avgTotalAmount":17.966673082342183,"numberOfTrips":188081},{"day":"Tuesday","weather":"sunny","season":"spring","time":"night","area":"not manhattan","avgDuration":1312.4399357469417,"avgDistance":10.526502409489682,"avgFareAmount":31.410323983689608,"avgTipAmount":5.36835265043865,"avgTotalAmount":42.416946991226986,"numberOfTrips":40465},{"day":"Tuesday","weather":"sunny","season":"summer","time":"day","area":"manhattan","avgDuration":831.7474597689734,"avgDistance":2.3933361072964363,"avgFareAmount":11.53399284020717,"avgTipAmount":2.270857223091702,"avgTotalAmount":17.622056579714908,"numberOfTrips":876003},{"day":"Tuesday","weather":"sunny","season":"summer","time":"day","area":"not manhattan","avgDuration":1827.3978819122026,"avgDistance":9.543675434664276,"avgFareAmount":30.715494300534726,"avgTipAmount":5.109014921072012,"avgTotalAmount":42.26409064711344,"numberOfTrips":124924},{"day":"Tuesday","weather":"sunny","season":"summer","time":"night","area":"manhattan","avgDuration":723.5611372839718,"avgDistance":2.9378248616990645,"avgFareAmount":11.843511281558037,"avgTipAmount":2.3939444100691656,"avgTotalAmount":18.180339886418633,"numberOfTrips":163231},{"day":"Tuesday","weather":"sunny","season":"summer","time":"night","area":"not manhattan","avgDuration":1394.0015638772784,"avgDistance":10.825377747448037,"avgFareAmount":32.47792772043561,"avgTipAmount":5.2705155108191875,"avgTotalAmount":43.36823935852597,"numberOfTrips":35169},{"day":"Tuesday","weather":"sunny","season":"winter","time":"day","area":"manhattan","avgDuration":797.1637729092922,"avgDistance":2.228139034290478,"avgFareAmount":11.701801035957851,"avgTipAmount":2.3084416077847174,"avgTotalAmount":17.964362858587652,"numberOfTrips":731690},{"day":"Tuesday","weather":"sunny","season":"winter","time":"day","area":"not manhattan","avgDuration":1692.2477310887482,"avgDistance":9.086622038343776,"avgFareAmount":31.835806766678008,"avgTipAmount":5.19375580259649,"avgTotalAmount":43.75463812648837,"numberOfTrips":91123},{"day":"Tuesday","weather":"sunny","season":"winter","time":"night","area":"manhattan","avgDuration":679.1415572524077,"avgDistance":2.8095555846236855,"avgFareAmount":12.239545365359145,"avgTipAmount":2.4542149969750975,"avgTotalAmount":18.86933133308262,"numberOfTrips":122318},{"day":"Tuesday","weather":"sunny","season":"winter","time":"night","area":"not manhattan","avgDuration":1257.291015001596,"avgDistance":10.41773619533993,"avgFareAmount":34.01160110118098,"avgTipAmount":5.455791174593042,"avgTotalAmount":45.41185804340888,"numberOfTrips":25064},{"day":"Wednesday","weather":"rainy","season":"fall","time":"day","area":"manhattan","avgDuration":919.7321685418045,"avgDistance":2.2933519523494375,"avgFareAmount":11.978646944628283,"avgTipAmount":2.408200529450695,"avgTotalAmount":18.23942700198544,"numberOfTrips":226650},{"day":"Wednesday","weather":"rainy","season":"fall","time":"day","area":"not manhattan","avgDuration":1946.9340140910642,"avgDistance":9.449231198981968,"avgFareAmount":31.092642850491945,"avgTipAmount":5.332037927930724,"avgTotalAmount":43.26515534312052,"numberOfTrips":32219},{"day":"Wednesday","weather":"rainy","season":"fall","time":"night","area":"manhattan","avgDuration":755.5189559806407,"avgDistance":3.0089427287393407,"avgFareAmount":12.135127333486977,"avgTipAmount":2.473960589997695,"avgTotalAmount":18.564945840055312,"numberOfTrips":17356},{"day":"Wednesday","weather":"rainy","season":"fall","time":"night","area":"not manhattan","avgDuration":1382.322807017544,"avgDistance":10.39114709851552,"avgFareAmount":31.25962213225371,"avgTipAmount":5.2024561403508764,"avgTotalAmount":42.17672874493927,"numberOfTrips":3705},{"day":"Wednesday","weather":"rainy","season":"spring","time":"day","area":"manhattan","avgDuration":851.1881728563144,"avgDistance":2.238796296296296,"avgFareAmount":11.4010768852583,"avgTipAmount":2.3066631369286235,"avgTotalAmount":17.364803532259284,"numberOfTrips":158652},{"day":"Wednesday","weather":"rainy","season":"spring","time":"day","area":"not manhattan","avgDuration":1848.455438921478,"avgDistance":8.975285067407636,"avgFareAmount":29.371541113512404,"avgTipAmount":5.156295667387053,"avgTotalAmount":40.74468817536277,"numberOfTrips":19434},{"day":"Wednesday","weather":"rainy","season":"spring","time":"night","area":"manhattan","avgDuration":687.1749181427275,"avgDistance":2.8180441043039175,"avgFareAmount":11.35681762594185,"avgTipAmount":2.395168645705945,"avgTotalAmount":17.6754625429011,"numberOfTrips":25349},{"day":"Wednesday","weather":"rainy","season":"spring","time":"night","area":"not manhattan","avgDuration":1267.6258665511266,"avgDistance":10.107010398613518,"avgFareAmount":30.30437608318891,"avgTipAmount":5.163771663778163,"avgTotalAmount":41.25181759098786,"numberOfTrips":4616},{"day":"Wednesday","weather":"rainy","season":"summer","time":"day","area":"manhattan","avgDuration":952.791519130943,"avgDistance":2.3910950874901165,"avgFareAmount":12.231917735226375,"avgTipAmount":2.4745812850218294,"avgTotalAmount":18.68973581078758,"numberOfTrips":58178},{"day":"Wednesday","weather":"rainy","season":"summer","time":"day","area":"not manhattan","avgDuration":2052.5704225352115,"avgDistance":9.244521658251395,"avgFareAmount":31.18627690672336,"avgTipAmount":5.343786872176454,"avgTotalAmount":43.14112277438215,"numberOfTrips":7526},{"day":"Wednesday","weather":"rainy","season":"summer","time":"night","area":"manhattan","avgDuration":718.1251232549691,"avgDistance":3.025295033473455,"avgFareAmount":11.93014998183611,"avgTipAmount":2.3028781981420936,"avgTotalAmount":18.152063417925163,"numberOfTrips":19269},{"day":"Wednesday","weather":"rainy","season":"summer","time":"night","area":"not manhattan","avgDuration":1301.1700943624485,"avgDistance":10.573305105250423,"avgFareAmount":31.940658117590125,"avgTipAmount":4.96604403580934,"avgTotalAmount":42.30230825066538,"numberOfTrips":4133},{"day":"Wednesday","weather":"rainy","season":"winter","time":"day","area":"manhattan","avgDuration":779.8613942982724,"avgDistance":2.3033227519687443,"avgFareAmount":11.050769489042183,"avgTipAmount":2.1775850070203284,"avgTotalAmount":16.664535742628654,"numberOfTrips":32762},{"day":"Wednesday","weather":"rainy","season":"winter","time":"day","area":"not manhattan","avgDuration":1898.9565654029625,"avgDistance":9.1641978408235,"avgFareAmount":29.965792116495106,"avgTipAmount":4.9049083605322625,"avgTotalAmount":40.63015566156164,"numberOfTrips":3983},{"day":"Wednesday","weather":"rainy","season":"winter","time":"night","area":"manhattan","avgDuration":735.7984822934233,"avgDistance":3.5080417369308603,"avgFareAmount":13.16581155143339,"avgTipAmount":2.601456576728499,"avgTotalAmount":19.897951096121417,"numberOfTrips":4744},{"day":"Wednesday","weather":"rainy","season":"winter","time":"night","area":"not manhattan","avgDuration":1417.3446852425182,"avgDistance":11.159556243550051,"avgFareAmount":33.45980392156863,"avgTipAmount":5.50640866873065,"avgTotalAmount":44.3253560371517,"numberOfTrips":969},{"day":"Wednesday","weather":"sunny","season":"fall","time":"day","area":"manhattan","avgDuration":956.8999291026586,"avgDistance":2.4162150620574483,"avgFareAmount":12.438309053857795,"avgTipAmount":2.501941034286565,"avgTotalAmount":18.79838798283699,"numberOfTrips":785643},{"day":"Wednesday","weather":"sunny","season":"fall","time":"day","area":"not manhattan","avgDuration":2098.9286129202605,"avgDistance":9.768647597254004,"avgFareAmount":32.25741339552896,"avgTipAmount":5.651929765886288,"avgTotalAmount":44.74472557648301,"numberOfTrips":113620},{"day":"Wednesday","weather":"sunny","season":"fall","time":"night","area":"manhattan","avgDuration":765.2776023188405,"avgDistance":2.9317984463768116,"avgFareAmount":12.062565565217392,"avgTipAmount":2.5262221449275364,"avgTotalAmount":18.522424301449277,"numberOfTrips":215625},{"day":"Wednesday","weather":"sunny","season":"fall","time":"night","area":"not manhattan","avgDuration":1359.1380966828478,"avgDistance":10.22978837985437,"avgFareAmount":31.048736599919092,"avgTipAmount":5.428011731391586,"avgTotalAmount":42.2391904328479,"numberOfTrips":39552},{"day":"Wednesday","weather":"sunny","season":"spring","time":"day","area":"manhattan","avgDuration":872.9857989367102,"avgDistance":2.388575266490342,"avgFareAmount":11.77436970425583,"avgTipAmount":2.3725000240442413,"avgTotalAmount":18.007560225481555,"numberOfTrips":935775},{"day":"Wednesday","weather":"sunny","season":"spring","time":"day","area":"not manhattan","avgDuration":1917.2194063151767,"avgDistance":9.220113498569141,"avgFareAmount":30.227528091704258,"avgTipAmount":5.195502982975214,"avgTotalAmount":42.0336380171703,"numberOfTrips":123702},{"day":"Wednesday","weather":"sunny","season":"spring","time":"night","area":"manhattan","avgDuration":715.1849155865895,"avgDistance":2.905651968052035,"avgFareAmount":11.71072614663542,"avgTipAmount":2.434657755033718,"avgTotalAmount":18.0638097469989,"numberOfTrips":209090},{"day":"Wednesday","weather":"sunny","season":"spring","time":"night","area":"not manhattan","avgDuration":1306.2817980960695,"avgDistance":9.989963176127219,"avgFareAmount":30.13930525626688,"avgTipAmount":5.1378628515316,"avgTotalAmount":40.91293118027331,"numberOfTrips":36661},{"day":"Wednesday","weather":"sunny","season":"summer","time":"day","area":"manhattan","avgDuration":863.535890869293,"avgDistance":2.4109119792343665,"avgFareAmount":11.761616520426783,"avgTipAmount":2.32794446224967,"avgTotalAmount":17.933526357411402,"numberOfTrips":1007819},{"day":"Wednesday","weather":"sunny","season":"summer","time":"day","area":"not manhattan","avgDuration":1882.665576747122,"avgDistance":9.459838427111334,"avgFareAmount":30.7044529005809,"avgTipAmount":5.072973636241125,"avgTotalAmount":42.25044655966068,"numberOfTrips":140989},{"day":"Wednesday","weather":"sunny","season":"summer","time":"night","area":"manhattan","avgDuration":744.3326926885476,"avgDistance":2.9300033307527498,"avgFareAmount":11.924252336027942,"avgTipAmount":2.43822421367229,"avgTotalAmount":18.293828880326956,"numberOfTrips":222172},{"day":"Wednesday","weather":"sunny","season":"summer","time":"night","area":"not manhattan","avgDuration":1401.0040995014804,"avgDistance":10.483547587114407,"avgFareAmount":31.70718627426171,"avgTipAmount":5.202176531619303,"avgTotalAmount":42.504921173165975,"numberOfTrips":39517},{"day":"Wednesday","weather":"sunny","season":"winter","time":"day","area":"manhattan","avgDuration":833.6974116296702,"avgDistance":2.257468549822449,"avgFareAmount":11.933817472087233,"avgTipAmount":2.3722636211952737,"avgTotalAmount":18.299798590230562,"numberOfTrips":808501},{"day":"Wednesday","weather":"sunny","season":"winter","time":"day","area":"not manhattan","avgDuration":1778.0248376590123,"avgDistance":8.969846467419137,"avgFareAmount":31.61071747546961,"avgTipAmount":5.261655775651924,"avgTotalAmount":43.68308949751111,"numberOfTrips":97634},{"day":"Wednesday","weather":"sunny","season":"winter","time":"night","area":"manhattan","avgDuration":706.3144153352341,"avgDistance":2.82219723731478,"avgFareAmount":12.238609571969086,"avgTipAmount":2.4946607611430895,"avgTotalAmount":18.84942761848405,"numberOfTrips":167301},{"day":"Wednesday","weather":"sunny","season":"winter","time":"night","area":"not manhattan","avgDuration":1263.5463671818575,"avgDistance":9.706295681063123,"avgFareAmount":31.970930954788386,"avgTipAmount":5.224881915354615,"avgTotalAmount":43.06727899754442,"numberOfTrips":27692},{"day":"Thursday","weather":"rainy","season":"fall","time":"day","area":"manhattan","avgDuration":1073.4415472809399,"avgDistance":2.4220714951948774,"avgFareAmount":13.2472103040275,"avgTipAmount":2.6232858235781134,"avgTotalAmount":19.715311835169096,"numberOfTrips":95419},{"day":"Thursday","weather":"rainy","season":"fall","time":"day","area":"not manhattan","avgDuration":2311.1735381494095,"avgDistance":10.006513296137962,"avgFareAmount":33.54114411999131,"avgTipAmount":5.803877979856532,"avgTotalAmount":46.278316788638506,"numberOfTrips":13801},{"day":"Thursday","weather":"rainy","season":"fall","time":"night","area":"manhattan","avgDuration":807.4779018612521,"avgDistance":2.6237516074450085,"avgFareAmount":11.60845752961083,"avgTipAmount":2.5014314720812183,"avgTotalAmount":17.98797089678511,"numberOfTrips":14775},{"day":"Thursday","weather":"rainy","season":"fall","time":"night","area":"not manhattan","avgDuration":1501.9194826866917,"avgDistance":10.363679599499374,"avgFareAmount":31.66374634960367,"avgTipAmount":5.726942010846892,"avgTotalAmount":43.58838548185231,"numberOfTrips":2397},{"day":"Thursday","weather":"rainy","season":"spring","time":"day","area":"manhattan","avgDuration":871.8264600839879,"avgDistance":2.361760168150044,"avgFareAmount":11.701860683153162,"avgTipAmount":2.3884342771423213,"avgTotalAmount":17.97312830598424,"numberOfTrips":229319},{"day":"Thursday","weather":"rainy","season":"spring","time":"day","area":"not manhattan","avgDuration":2023.6942777953197,"avgDistance":9.27598673823808,"avgFareAmount":30.319097989685297,"avgTipAmount":5.171692453425955,"avgTotalAmount":42.082687085569944,"numberOfTrips":28503},{"day":"Thursday","weather":"rainy","season":"spring","time":"night","area":"manhattan","avgDuration":742.4344112670051,"avgDistance":2.8114628719137653,"avgFareAmount":11.650733634461899,"avgTipAmount":2.443204221129632,"avgTotalAmount":17.997628012951193,"numberOfTrips":75051},{"day":"Thursday","weather":"rainy","season":"spring","time":"night","area":"not manhattan","avgDuration":1342.9147229114972,"avgDistance":9.864344913151363,"avgFareAmount":29.915852770885028,"avgTipAmount":5.271239040529363,"avgTotalAmount":40.823898263027296,"numberOfTrips":12090},{"day":"Thursday","weather":"rainy","season":"summer","time":"day","area":"manhattan","avgDuration":912.0378797356185,"avgDistance":2.4330519067575738,"avgFareAmount":12.100861324826422,"avgTipAmount":2.3846819811930526,"avgTotalAmount":18.295990700777715,"numberOfTrips":191844},{"day":"Thursday","weather":"rainy","season":"summer","time":"day","area":"not manhattan","avgDuration":2007.654526862267,"avgDistance":9.285627310626916,"avgFareAmount":30.814281444190986,"avgTipAmount":5.118715094784866,"avgTotalAmount":42.31220286321089,"numberOfTrips":25426},{"day":"Thursday","weather":"rainy","season":"summer","time":"night","area":"manhattan","avgDuration":744.8596026490067,"avgDistance":3.2883669653291783,"avgFareAmount":12.745389949357225,"avgTipAmount":2.4808500194779897,"avgTotalAmount":19.277155434359173,"numberOfTrips":12835},{"day":"Thursday","weather":"rainy","season":"summer","time":"night","area":"not manhattan","avgDuration":1331.2160674981658,"avgDistance":10.6854402054292,"avgFareAmount":32.28951577402788,"avgTipAmount":5.108411592076303,"avgTotalAmount":43.01838958180485,"numberOfTrips":2726},{"day":"Thursday","weather":"rainy","season":"winter","time":"day","area":"manhattan","avgDuration":912.0493465656971,"avgDistance":2.231115095436096,"avgFareAmount":12.54077916578446,"avgTipAmount":2.4918109207544794,"avgTotalAmount":19.12604276942621,"numberOfTrips":221981},{"day":"Thursday","weather":"rainy","season":"winter","time":"day","area":"not manhattan","avgDuration":2109.2986979359325,"avgDistance":9.147206480727972,"avgFareAmount":33.54260116889843,"avgTipAmount":5.401708219279426,"avgTotalAmount":46.058013242583414,"numberOfTrips":27034},{"day":"Thursday","weather":"rainy","season":"winter","time":"night","area":"manhattan","avgDuration":742.8678756476684,"avgDistance":2.670025043177893,"avgFareAmount":12.016097582037997,"avgTipAmount":2.5317861830742663,"avgTotalAmount":18.645808635578586,"numberOfTrips":57900},{"day":"Thursday","weather":"rainy","season":"winter","time":"night","area":"not manhattan","avgDuration":1358.8707514450866,"avgDistance":9.466612716763006,"avgFareAmount":31.236485549132944,"avgTipAmount":5.369665895953757,"avgTotalAmount":42.64666936416185,"numberOfTrips":8650},{"day":"Thursday","weather":"sunny","season":"fall","time":"day","area":"manhattan","avgDuration":962.8336348254945,"avgDistance":2.50187915114207,"avgFareAmount":12.58124106773224,"avgTipAmount":2.513640292852386,"avgTotalAmount":18.985745799359215,"numberOfTrips":888912},{"day":"Thursday","weather":"sunny","season":"fall","time":"day","area":"not manhattan","avgDuration":2177.098320124379,"avgDistance":9.811126919722422,"avgFareAmount":32.51599499450153,"avgTipAmount":5.504088885518183,"avgTotalAmount":44.82120678017519,"numberOfTrips":131855},{"day":"Thursday","weather":"sunny","season":"fall","time":"night","area":"manhattan","avgDuration":800.6388037276918,"avgDistance":2.973050575599456,"avgFareAmount":12.38194343491767,"avgTipAmount":2.551662680445861,"avgTotalAmount":18.889505898117882,"numberOfTrips":246265},{"day":"Thursday","weather":"sunny","season":"fall","time":"night","area":"not manhattan","avgDuration":1419.6805248957567,"avgDistance":10.073601422614667,"avgFareAmount":30.876921756193283,"avgTipAmount":5.248345597252881,"avgTotalAmount":41.891851851851854,"numberOfTrips":40770},{"day":"Thursday","weather":"sunny","season":"spring","time":"day","area":"manhattan","avgDuration":892.039978850446,"avgDistance":2.455957017316484,"avgFareAmount":12.013401499737352,"avgTipAmount":2.40878516228039,"avgTotalAmount":18.28430066545397,"numberOfTrips":871886},{"day":"Thursday","weather":"sunny","season":"spring","time":"day","area":"not manhattan","avgDuration":2020.3252497422434,"avgDistance":9.396615202003137,"avgFareAmount":30.836444172969788,"avgTipAmount":5.266941837998943,"avgTotalAmount":42.744569178384836,"numberOfTrips":115419},{"day":"Thursday","weather":"sunny","season":"spring","time":"night","area":"manhattan","avgDuration":726.7877180826956,"avgDistance":2.9231712831519556,"avgFareAmount":11.818318425480708,"avgTipAmount":2.435160947503868,"avgTotalAmount":18.185121719968535,"numberOfTrips":191957},{"day":"Thursday","weather":"sunny","season":"spring","time":"night","area":"not manhattan","avgDuration":1336.3512477298716,"avgDistance":9.997136611286741,"avgFareAmount":30.30603080648416,"avgTipAmount":5.168175489338804,"avgTotalAmount":41.12555861976189,"numberOfTrips":29734},{"day":"Thursday","weather":"sunny","season":"summer","time":"day","area":"manhattan","avgDuration":875.3380105891796,"avgDistance":2.470782234527991,"avgFareAmount":11.93132302152446,"avgTipAmount":2.363529076060943,"avgTotalAmount":18.190417811127723,"numberOfTrips":814794},{"day":"Thursday","weather":"sunny","season":"summer","time":"day","area":"not manhattan","avgDuration":1956.9611310803402,"avgDistance":9.506740267539318,"avgFareAmount":31.002969477541143,"avgTipAmount":5.10829807047929,"avgTotalAmount":42.619424538072565,"numberOfTrips":114899},{"day":"Thursday","weather":"sunny","season":"summer","time":"night","area":"manhattan","avgDuration":767.5933523781721,"avgDistance":2.9314040494609754,"avgFareAmount":12.06362820860354,"avgTipAmount":2.456988677356799,"avgTotalAmount":18.446214608920492,"numberOfTrips":239785},{"day":"Thursday","weather":"sunny","season":"summer","time":"night","area":"not manhattan","avgDuration":1435.9287196206283,"avgDistance":10.486529095040506,"avgFareAmount":31.8654581604426,"avgTipAmount":5.248634904169137,"avgTotalAmount":42.802034182967795,"numberOfTrips":40488},{"day":"Thursday","weather":"sunny","season":"winter","time":"day","area":"manhattan","avgDuration":840.4027264874879,"avgDistance":2.3091528304589906,"avgFareAmount":11.874660788625587,"avgTipAmount":2.364672931384372,"avgTotalAmount":18.155446145543415,"numberOfTrips":718947},{"day":"Thursday","weather":"sunny","season":"winter","time":"day","area":"not manhattan","avgDuration":1893.961760636078,"avgDistance":9.331371213951547,"avgFareAmount":32.046249203804166,"avgTipAmount":5.37374343824815,"avgTotalAmount":44.28578752004217,"numberOfTrips":91058},{"day":"Thursday","weather":"sunny","season":"winter","time":"night","area":"manhattan","avgDuration":718.8174224713666,"avgDistance":2.864598947061632,"avgFareAmount":12.233730303913482,"avgTipAmount":2.4943682679845964,"avgTotalAmount":18.798247769172097,"numberOfTrips":161263},{"day":"Thursday","weather":"sunny","season":"winter","time":"night","area":"not manhattan","avgDuration":1277.3222653027553,"avgDistance":9.796164824286421,"avgFareAmount":31.805694604850686,"avgTipAmount":5.269075235109718,"avgTotalAmount":42.88807746246494,"numberOfTrips":24244},{"day":"Friday","weather":"rainy","season":"fall","time":"day","area":"manhattan","avgDuration":911.9416511135123,"avgDistance":2.39429267060524,"avgFareAmount":12.14626092813741,"avgTipAmount":2.3818830777002846,"avgTotalAmount":18.151022438641053,"numberOfTrips":71261},{"day":"Friday","weather":"rainy","season":"fall","time":"day","area":"not manhattan","avgDuration":2119.1026147479306,"avgDistance":9.948022949586155,"avgFareAmount":32.71565650865312,"avgTipAmount":5.613528028592927,"avgTotalAmount":44.75079288939052,"numberOfTrips":10632},{"day":"Friday","weather":"rainy","season":"fall","time":"night","area":"manhattan","avgDuration":817.9030739338382,"avgDistance":2.713741530490235,"avgFareAmount":11.948737046632123,"avgTipAmount":2.461546183738541,"avgTotalAmount":18.328415952570747,"numberOfTrips":40144},{"day":"Friday","weather":"rainy","season":"fall","time":"night","area":"not manhattan","avgDuration":1466.7760292481323,"avgDistance":10.429464314099507,"avgFareAmount":31.747138769670958,"avgTipAmount":5.676048323001112,"avgTotalAmount":43.36499443649658,"numberOfTrips":6291},{"day":"Friday","weather":"rainy","season":"spring","time":"day","area":"manhattan","avgDuration":902.1253597900384,"avgDistance":2.4336837885386324,"avgFareAmount":11.956593314682895,"avgTipAmount":2.4049388284832576,"avgTotalAmount":18.355326680702564,"numberOfTrips":173365},{"day":"Friday","weather":"rainy","season":"spring","time":"day","area":"not manhattan","avgDuration":2325.5250668178505,"avgDistance":9.749429011095813,"avgFareAmount":32.57712683242893,"avgTipAmount":5.542543532841986,"avgTotalAmount":44.903982343889204,"numberOfTrips":24694},{"day":"Friday","weather":"rainy","season":"spring","time":"night","area":"manhattan","avgDuration":754.9475109153655,"avgDistance":2.7648216362561726,"avgFareAmount":11.668344105702682,"avgTipAmount":2.345771130050144,"avgTotalAmount":17.89855364258613,"numberOfTrips":52449},{"day":"Friday","weather":"rainy","season":"spring","time":"night","area":"not manhattan","avgDuration":1423.4236015649783,"avgDistance":10.61618800888231,"avgFareAmount":32.09628106164746,"avgTipAmount":5.4490811039441684,"avgTotalAmount":43.38062493391139,"numberOfTrips":9457},{"day":"Friday","weather":"rainy","season":"summer","time":"day","area":"manhattan","avgDuration":859.4619171209837,"avgDistance":2.484621128639369,"avgFareAmount":11.818088751304952,"avgTipAmount":2.2766712823338358,"avgTotalAmount":17.947842767660365,"numberOfTrips":137936},{"day":"Friday","weather":"rainy","season":"summer","time":"day","area":"not manhattan","avgDuration":2082.487439897949,"avgDistance":9.78657590030419,"avgFareAmount":31.98083750367972,"avgTipAmount":5.155221273672849,"avgTotalAmount":43.83377293690511,"numberOfTrips":20382},{"day":"Friday","weather":"rainy","season":"summer","time":"night","area":"manhattan","avgDuration":730.688319340109,"avgDistance":3.2772941523051995,"avgFareAmount":12.575796140816026,"avgTipAmount":2.463449698040949,"avgTotalAmount":19.011143025482397,"numberOfTrips":6789},{"day":"Friday","weather":"rainy","season":"summer","time":"night","area":"not manhattan","avgDuration":1270.9206598586018,"avgDistance":11.002757266300078,"avgFareAmount":33.602160251374706,"avgTipAmount":5.392686567164179,"avgTotalAmount":44.50865671641791,"numberOfTrips":1273},{"day":"Friday","weather":"rainy","season":"winter","time":"day","area":"manhattan","avgDuration":810.7015201674144,"avgDistance":2.2100687294843886,"avgFareAmount":11.521308939732222,"avgTipAmount":2.307122390274288,"avgTotalAmount":17.6526504594797,"numberOfTrips":285758},{"day":"Friday","weather":"rainy","season":"winter","time":"day","area":"not manhattan","avgDuration":1890.1001953751495,"avgDistance":9.404456594640306,"avgFareAmount":31.995574607062665,"avgTipAmount":5.216329571632695,"avgTotalAmount":43.80284781150672,"numberOfTrips":34293},{"day":"Friday","weather":"rainy","season":"winter","time":"night","area":"manhattan","avgDuration":743.8033235030982,"avgDistance":2.89006362039829,"avgFareAmount":12.238953908346865,"avgTipAmount":2.48318698432685,"avgTotalAmount":18.759528148712683,"numberOfTrips":60358},{"day":"Friday","weather":"rainy","season":"winter","time":"night","area":"not manhattan","avgDuration":1375.726510067114,"avgDistance":10.052501290655654,"avgFareAmount":32.017392875580796,"avgTipAmount":5.231482963345379,"avgTotalAmount":43.091072534847704,"numberOfTrips":7748},{"day":"Friday","weather":"sunny","season":"fall","time":"day","area":"manhattan","avgDuration":920.8025400668743,"avgDistance":2.538816545601291,"avgFareAmount":12.362273008186326,"avgTipAmount":2.443599953879857,"avgTotalAmount":18.731226611322494,"numberOfTrips":867300},{"day":"Friday","weather":"sunny","season":"fall","time":"day","area":"not manhattan","avgDuration":2226.0913682725286,"avgDistance":10.139844041999083,"avgFareAmount":33.265345576811946,"avgTipAmount":5.715082894904722,"avgTotalAmount":45.884179794507695,"numberOfTrips":133241},{"day":"Friday","weather":"sunny","season":"fall","time":"night","area":"manhattan","avgDuration":812.0217952710452,"avgDistance":2.8628150421170164,"avgFareAmount":12.251761585027761,"avgTipAmount":2.468794139316558,"avgTotalAmount":18.663416415382397,"numberOfTrips":263314},{"day":"Friday","weather":"sunny","season":"fall","time":"night","area":"not manhattan","avgDuration":1424.6582384285864,"avgDistance":10.02117803782259,"avgFareAmount":30.72971319611326,"avgTipAmount":5.153386009821336,"avgTotalAmount":41.58877024344373,"numberOfTrips":38284},{"day":"Friday","weather":"sunny","season":"spring","time":"day","area":"manhattan","avgDuration":843.4375984857882,"avgDistance":2.488243909386184,"avgFareAmount":11.73834709263062,"avgTipAmount":2.3376691313955464,"avgTotalAmount":17.93620090641381,"numberOfTrips":870684},{"day":"Friday","weather":"sunny","season":"spring","time":"day","area":"not manhattan","avgDuration":2027.781391843516,"avgDistance":9.748505129917955,"avgFareAmount":31.506558330335885,"avgTipAmount":5.39584947673124,"avgTotalAmount":43.55371375229091,"numberOfTrips":116766},{"day":"Friday","weather":"sunny","season":"spring","time":"night","area":"manhattan","avgDuration":754.5317526902729,"avgDistance":2.824627116111756,"avgFareAmount":11.818220033482357,"avgTipAmount":2.3962682879176196,"avgTotalAmount":18.135997096152597,"numberOfTrips":261033},{"day":"Friday","weather":"sunny","season":"spring","time":"night","area":"not manhattan","avgDuration":1376.0031443794219,"avgDistance":9.876917925874167,"avgFareAmount":30.182647683931638,"avgTipAmount":5.171947768364049,"avgTotalAmount":40.9817669665473,"numberOfTrips":34347},{"day":"Friday","weather":"sunny","season":"summer","time":"day","area":"manhattan","avgDuration":837.7775344440801,"avgDistance":2.5509275308005805,"avgFareAmount":11.814946050186599,"avgTipAmount":2.292273101086283,"avgTotalAmount":18.01715000286275,"numberOfTrips":768492},{"day":"Friday","weather":"sunny","season":"summer","time":"day","area":"not manhattan","avgDuration":1988.0675893927028,"avgDistance":10.015436066200094,"avgFareAmount":32.17423840369553,"avgTipAmount":5.245348974523731,"avgTotalAmount":44.021142090547556,"numberOfTrips":115166},{"day":"Friday","weather":"sunny","season":"summer","time":"night","area":"manhattan","avgDuration":787.3323588944418,"avgDistance":2.8762965948376236,"avgFareAmount":12.11021086571014,"avgTipAmount":2.386385261611765,"avgTotalAmount":18.4239523528042,"numberOfTrips":279135},{"day":"Friday","weather":"sunny","season":"summer","time":"night","area":"not manhattan","avgDuration":1488.4258035797957,"avgDistance":10.532345375316277,"avgFareAmount":32.12051986692906,"avgTipAmount":5.22766985287227,"avgTotalAmount":42.97656920625995,"numberOfTrips":42684},{"day":"Friday","weather":"sunny","season":"winter","time":"day","area":"manhattan","avgDuration":811.376843952867,"avgDistance":2.303889869390705,"avgFareAmount":11.72817671295639,"avgTipAmount":2.3335792367358,"avgTotalAmount":18.106471258211478,"numberOfTrips":619864},{"day":"Friday","weather":"sunny","season":"winter","time":"day","area":"not manhattan","avgDuration":1891.157826963726,"avgDistance":9.578554994047474,"avgFareAmount":32.83291491532836,"avgTipAmount":5.554657790519692,"avgTotalAmount":45.51897264267839,"numberOfTrips":82318},{"day":"Friday","weather":"sunny","season":"winter","time":"night","area":"manhattan","avgDuration":747.6355617788043,"avgDistance":2.655096585276111,"avgFareAmount":11.983801167199845,"avgTipAmount":2.4409336065657548,"avgTotalAmount":18.472205772631106,"numberOfTrips":195682},{"day":"Friday","weather":"sunny","season":"winter","time":"night","area":"not manhattan","avgDuration":1310.1935186299281,"avgDistance":9.544742710464044,"avgFareAmount":31.51367785665584,"avgTipAmount":5.255000601612321,"avgTotalAmount":42.6815882565275,"numberOfTrips":24933},{"day":"Saturday","weather":"rainy","season":"fall","time":"day","area":"manhattan","avgDuration":797.2832714810803,"avgDistance":2.477523838272635,"avgFareAmount":11.560563240229415,"avgTipAmount":2.2394019567803682,"avgTotalAmount":17.317900989044162,"numberOfTrips":56317},{"day":"Saturday","weather":"rainy","season":"fall","time":"day","area":"not manhattan","avgDuration":1654.0375867847738,"avgDistance":10.068053627005028,"avgFareAmount":31.722019391908066,"avgTipAmount":5.208395977974623,"avgTotalAmount":42.67604620541058,"numberOfTrips":8354},{"day":"Saturday","weather":"rainy","season":"fall","time":"night","area":"manhattan","avgDuration":770.9664905948995,"avgDistance":2.915116518081216,"avgFareAmount":12.050913023733838,"avgTipAmount":2.4213991730203874,"avgTotalAmount":18.400199096536724,"numberOfTrips":41839},{"day":"Saturday","weather":"rainy","season":"fall","time":"night","area":"not manhattan","avgDuration":1278.7,"avgDistance":9.368344262295082,"avgFareAmount":29.002126463700236,"avgTipAmount":4.760779859484777,"avgTotalAmount":38.835067915690864,"numberOfTrips":4270},{"day":"Saturday","weather":"rainy","season":"spring","time":"day","area":"manhattan","avgDuration":776.9263805532171,"avgDistance":2.389557673796872,"avgFareAmount":11.221959493915337,"avgTipAmount":2.176381488622751,"avgTotalAmount":16.870238045665904,"numberOfTrips":331407},{"day":"Saturday","weather":"rainy","season":"spring","time":"day","area":"not manhattan","avgDuration":1639.130196001855,"avgDistance":9.459377822255853,"avgFareAmount":29.93729136664307,"avgTipAmount":4.934891259244795,"avgTotalAmount":40.64064512192145,"numberOfTrips":40969},{"day":"Saturday","weather":"rainy","season":"spring","time":"night","area":"manhattan","avgDuration":760.2294913225613,"avgDistance":2.697613405146619,"avgFareAmount":11.545253979652902,"avgTipAmount":2.29329144225015,"avgTotalAmount":17.713614961101136,"numberOfTrips":83550},{"day":"Saturday","weather":"rainy","season":"spring","time":"night","area":"not manhattan","avgDuration":1377.9368207211783,"avgDistance":9.72419908583037,"avgFareAmount":29.701056373793808,"avgTipAmount":4.877465718638903,"avgTotalAmount":39.97168715083799,"numberOfTrips":9845},{"day":"Saturday","weather":"rainy","season":"summer","time":"day","area":"manhattan","avgDuration":770.108802408194,"avgDistance":2.631209454202222,"avgFareAmount":11.632766489368487,"avgTipAmount":2.1437807880202553,"avgTotalAmount":17.281209836860164,"numberOfTrips":78399},{"day":"Saturday","weather":"rainy","season":"summer","time":"day","area":"not manhattan","avgDuration":1733.7050503218786,"avgDistance":10.126176443920574,"avgFareAmount":31.823555172726447,"avgTipAmount":4.999253785474657,"avgTotalAmount":42.646997007888295,"numberOfTrips":11029},{"day":"Saturday","weather":"rainy","season":"summer","time":"night","area":"manhattan","avgDuration":757.2079915321514,"avgDistance":2.937832759989415,"avgFareAmount":12.11057819528976,"avgTipAmount":2.360832230748875,"avgTotalAmount":18.398242921407782,"numberOfTrips":7558},{"day":"Saturday","weather":"rainy","season":"summer","time":"night","area":"not manhattan","avgDuration":1547.0064446831364,"avgDistance":10.557303974221268,"avgFareAmount":32.44127819548872,"avgTipAmount":5.073361976369496,"avgTotalAmount":42.85996777658431,"numberOfTrips":931},{"day":"Saturday","weather":"rainy","season":"winter","time":"day","area":"manhattan","avgDuration":768.8576804056312,"avgDistance":2.377924118493121,"avgFareAmount":11.91009639551946,"avgTipAmount":2.2448319071348664,"avgTotalAmount":17.775766369804302,"numberOfTrips":137662},{"day":"Saturday","weather":"rainy","season":"winter","time":"day","area":"not manhattan","avgDuration":1581.1683771815576,"avgDistance":10.248500651211254,"avgFareAmount":34.32956238603803,"avgTipAmount":5.660965876530347,"avgTotalAmount":46.16276530346445,"numberOfTrips":19195},{"day":"Saturday","weather":"rainy","season":"winter","time":"night","area":"manhattan","avgDuration":734.5533285612025,"avgDistance":2.6365575584043732,"avgFareAmount":12.334858788312618,"avgTipAmount":2.4456217869460533,"avgTotalAmount":18.98107665777315,"numberOfTrips":30734},{"day":"Saturday","weather":"rainy","season":"winter","time":"night","area":"not manhattan","avgDuration":1389.3632075471698,"avgDistance":10.690387612797375,"avgFareAmount":37.06833059885152,"avgTipAmount":6.108630024610337,"avgTotalAmount":49.46301271534044,"numberOfTrips":4876},{"day":"Saturday","weather":"sunny","season":"fall","time":"day","area":"manhattan","avgDuration":875.9990844884547,"avgDistance":2.5633980141815034,"avgFareAmount":12.238222607014755,"avgTipAmount":2.3113823204264907,"avgTotalAmount":18.080511577140772,"numberOfTrips":784261},{"day":"Saturday","weather":"sunny","season":"fall","time":"day","area":"not manhattan","avgDuration":1854.3794279084298,"avgDistance":10.17057262706948,"avgFareAmount":32.28251015217101,"avgTipAmount":5.306741398545227,"avgTotalAmount":43.49633718595207,"numberOfTrips":112045},{"day":"Saturday","weather":"sunny","season":"fall","time":"night","area":"manhattan","avgDuration":830.2189849682608,"avgDistance":2.809333352021778,"avgFareAmount":12.230493156914413,"avgTipAmount":2.4500614538364265,"avgTotalAmount":18.57561298099385,"numberOfTrips":321054},{"day":"Saturday","weather":"sunny","season":"fall","time":"night","area":"not manhattan","avgDuration":1383.8940522482064,"avgDistance":9.575308614929623,"avgFareAmount":29.7374004600471,"avgTipAmount":4.856451612903226,"avgTotalAmount":39.83260309984117,"numberOfTrips":36518},{"day":"Saturday","weather":"sunny","season":"spring","time":"day","area":"manhattan","avgDuration":809.7140062409387,"avgDistance":2.5305026961586177,"avgFareAmount":11.72199362952605,"avgTipAmount":2.2402256071131426,"avgTotalAmount":17.47165906339419,"numberOfTrips":602153},{"day":"Saturday","weather":"sunny","season":"spring","time":"day","area":"not manhattan","avgDuration":1692.3723763431199,"avgDistance":9.918835898686728,"avgFareAmount":31.15214770787065,"avgTipAmount":5.123300768964145,"avgTotalAmount":42.108624465640524,"numberOfTrips":77897},{"day":"Saturday","weather":"sunny","season":"spring","time":"night","area":"manhattan","avgDuration":755.7451503016002,"avgDistance":2.7969632928430186,"avgFareAmount":11.723618438325662,"avgTipAmount":2.3674392063676697,"avgTotalAmount":17.972574751989896,"numberOfTrips":300895},{"day":"Saturday","weather":"sunny","season":"spring","time":"night","area":"not manhattan","avgDuration":1333.8716629335916,"avgDistance":9.387047944790845,"avgFareAmount":28.98272353048005,"avgTipAmount":4.749792360312367,"avgTotalAmount":38.9374556571221,"numberOfTrips":33038},{"day":"Saturday","weather":"sunny","season":"summer","time":"day","area":"manhattan","avgDuration":790.4065890072006,"avgDistance":2.6121866468347745,"avgFareAmount":11.74524473852484,"avgTipAmount":2.1853777975478885,"avgTotalAmount":17.462351663932832,"numberOfTrips":719380},{"day":"Saturday","weather":"sunny","season":"summer","time":"day","area":"not manhattan","avgDuration":1734.4299372425967,"avgDistance":10.075732986860169,"avgFareAmount":31.71994381251226,"avgTipAmount":5.028238870366739,"avgTotalAmount":42.5158981172779,"numberOfTrips":101980},{"day":"Saturday","weather":"sunny","season":"summer","time":"night","area":"manhattan","avgDuration":779.4998642321958,"avgDistance":2.8679582014197433,"avgFareAmount":12.003318224813581,"avgTipAmount":2.3400260793540437,"avgTotalAmount":18.23229623639711,"numberOfTrips":335131},{"day":"Saturday","weather":"sunny","season":"summer","time":"night","area":"not manhattan","avgDuration":1473.7032640243613,"avgDistance":9.990997050007138,"avgFareAmount":30.816817338345153,"avgTipAmount":4.815487224627683,"avgTotalAmount":40.87978945615454,"numberOfTrips":42034},{"day":"Saturday","weather":"sunny","season":"winter","time":"day","area":"manhattan","avgDuration":765.687271776123,"avgDistance":2.310256039296993,"avgFareAmount":11.359941154999387,"avgTipAmount":2.2107343507321637,"avgTotalAmount":17.07521155088053,"numberOfTrips":676693},{"day":"Saturday","weather":"sunny","season":"winter","time":"day","area":"not manhattan","avgDuration":1550.6685635892486,"avgDistance":9.396028021950105,"avgFareAmount":30.89026827905086,"avgTipAmount":5.00888610842945,"avgTotalAmount":41.705553452568466,"numberOfTrips":78724},{"day":"Saturday","weather":"sunny","season":"winter","time":"night","area":"manhattan","avgDuration":750.5489532098987,"avgDistance":2.688314449051065,"avgFareAmount":11.806667074395488,"avgTipAmount":2.406679338449257,"avgTotalAmount":18.158489911930577,"numberOfTrips":310664},{"day":"Saturday","weather":"sunny","season":"winter","time":"night","area":"not manhattan","avgDuration":1262.2804914794604,"avgDistance":9.157990893568584,"avgFareAmount":29.788648766279422,"avgTipAmount":4.754527436472597,"avgTotalAmount":39.69865981452342,"numberOfTrips":29869},{"day":"Sunday","weather":"rainy","season":"fall","time":"day","area":"manhattan","avgDuration":845.9419909573217,"avgDistance":2.748956014949168,"avgFareAmount":12.366380419726628,"avgTipAmount":2.344351880406659,"avgTotalAmount":18.35655008755194,"numberOfTrips":191315},{"day":"Sunday","weather":"rainy","season":"fall","time":"day","area":"not manhattan","avgDuration":1899.8284572720343,"avgDistance":11.272214599269248,"avgFareAmount":34.82532476408275,"avgTipAmount":6.022521620271798,"avgTotalAmount":47.20505796072865,"numberOfTrips":38043},{"day":"Sunday","weather":"rainy","season":"fall","time":"night","area":"manhattan","avgDuration":741.8069214635283,"avgDistance":2.861077604288045,"avgFareAmount":11.760580517361921,"avgTipAmount":2.2245019808902353,"avgTotalAmount":17.90052481938942,"numberOfTrips":42910},{"day":"Sunday","weather":"rainy","season":"fall","time":"night","area":"not manhattan","avgDuration":1490.5924016800304,"avgDistance":11.587976326842305,"avgFareAmount":34.451852806414664,"avgTipAmount":5.733295150820924,"avgTotalAmount":46.33275582283314,"numberOfTrips":10476},{"day":"Sunday","weather":"rainy","season":"spring","time":"day","area":"manhattan","avgDuration":730.8781411167449,"avgDistance":2.6516018842045814,"avgFareAmount":11.453157470101596,"avgTipAmount":2.2215570133247273,"avgTotalAmount":17.259202502342845,"numberOfTrips":161129},{"day":"Sunday","weather":"rainy","season":"spring","time":"day","area":"not manhattan","avgDuration":1672.5914078916646,"avgDistance":10.617980387578799,"avgFareAmount":32.61106856564713,"avgTipAmount":5.766535138921317,"avgTotalAmount":44.61376605183283,"numberOfTrips":25698},{"day":"Sunday","weather":"rainy","season":"spring","time":"night","area":"manhattan","avgDuration":745.138131426017,"avgDistance":2.911446619113331,"avgFareAmount":11.62689801947484,"avgTipAmount":2.311820567141552,"avgTotalAmount":17.821968474859574,"numberOfTrips":51451},{"day":"Sunday","weather":"rainy","season":"spring","time":"night","area":"not manhattan","avgDuration":1310.3105310531053,"avgDistance":10.084033903390338,"avgFareAmount":30.435643564356436,"avgTipAmount":5.081573657365736,"avgTotalAmount":40.77754425442544,"numberOfTrips":6666},{"day":"Sunday","weather":"rainy","season":"summer","time":"day","area":"manhattan","avgDuration":805.1108693172346,"avgDistance":2.888670445670963,"avgFareAmount":12.421246457183472,"avgTipAmount":2.3196660319577407,"avgTotalAmount":18.395453699885053,"numberOfTrips":113963},{"day":"Sunday","weather":"rainy","season":"summer","time":"day","area":"not manhattan","avgDuration":1845.05142089953,"avgDistance":11.234167375251735,"avgFareAmount":34.71158603714478,"avgTipAmount":5.765331394047886,"avgTotalAmount":46.702376818080104,"numberOfTrips":22345},{"day":"Sunday","weather":"rainy","season":"summer","time":"night","area":"manhattan","avgDuration":721.8675321453674,"avgDistance":2.906624219622111,"avgFareAmount":11.777437879852814,"avgTipAmount":2.3144387480878157,"avgTotalAmount":17.995331789804442,"numberOfTrips":24187},{"day":"Sunday","weather":"rainy","season":"summer","time":"night","area":"not manhattan","avgDuration":1561.6133449250162,"avgDistance":11.601595305368399,"avgFareAmount":34.68031732232124,"avgTipAmount":5.985933492718974,"avgTotalAmount":46.57575961747446,"numberOfTrips":4601},{"day":"Sunday","weather":"rainy","season":"winter","time":"day","area":"manhattan","avgDuration":727.9025751690405,"avgDistance":2.467765717162998,"avgFareAmount":11.041832757876564,"avgTipAmount":2.2055724356207738,"avgTotalAmount":16.757277945619336,"numberOfTrips":139020},{"day":"Sunday","weather":"rainy","season":"winter","time":"day","area":"not manhattan","avgDuration":1622.9317172793465,"avgDistance":10.629531610726337,"avgFareAmount":32.60253684958267,"avgTipAmount":5.629737613212573,"avgTotalAmount":44.236543242763275,"numberOfTrips":22524},{"day":"Sunday","weather":"rainy","season":"winter","time":"night","area":"manhattan","avgDuration":652.4855858361142,"avgDistance":2.721804783092325,"avgFareAmount":10.973319892473118,"avgTipAmount":2.1442737300704486,"avgTotalAmount":16.98287078235076,"numberOfTrips":21576},{"day":"Sunday","weather":"rainy","season":"winter","time":"night","area":"not manhattan","avgDuration":1394.5154010369015,"avgDistance":11.86714242146996,"avgFareAmount":34.68497102775236,"avgTipAmount":6.060939310765477,"avgTotalAmount":46.617285757853,"numberOfTrips":6558},{"day":"Sunday","weather":"sunny","season":"fall","time":"day","area":"manhattan","avgDuration":807.5627058186433,"avgDistance":2.8407174145310314,"avgFareAmount":12.38900995874741,"avgTipAmount":2.3708257836005795,"avgTotalAmount":18.429296824198733,"numberOfTrips":478273},{"day":"Sunday","weather":"sunny","season":"fall","time":"day","area":"not manhattan","avgDuration":1725.7484761461537,"avgDistance":10.934642504455214,"avgFareAmount":33.866110966072256,"avgTipAmount":5.798995902337143,"avgTotalAmount":45.86610415555228,"numberOfTrips":88099},{"day":"Sunday","weather":"sunny","season":"fall","time":"night","area":"manhattan","avgDuration":750.276155385735,"avgDistance":3.0209689774381365,"avgFareAmount":12.149932723799127,"avgTipAmount":2.4122906659388645,"avgTotalAmount":18.48766593886463,"numberOfTrips":219840},{"day":"Sunday","weather":"sunny","season":"fall","time":"night","area":"not manhattan","avgDuration":1299.192507204611,"avgDistance":10.337871757925072,"avgFareAmount":31.268007204610953,"avgTipAmount":5.346088760806916,"avgTotalAmount":42.1934674351585,"numberOfTrips":34700},{"day":"Sunday","weather":"sunny","season":"spring","time":"day","area":"manhattan","avgDuration":769.8996001319825,"avgDistance":2.823475584855979,"avgFareAmount":12.063455460779284,"avgTipAmount":2.29164842649975,"avgTotalAmount":17.98212534424912,"numberOfTrips":612202},{"day":"Sunday","weather":"sunny","season":"spring","time":"day","area":"not manhattan","avgDuration":1763.4317507559026,"avgDistance":10.868907045297291,"avgFareAmount":33.61184051638342,"avgTipAmount":5.798063183037448,"avgTotalAmount":45.56212249888629,"numberOfTrips":105503},{"day":"Sunday","weather":"sunny","season":"spring","time":"night","area":"manhattan","avgDuration":710.9214762294654,"avgDistance":2.9587194484608816,"avgFareAmount":11.796403715833668,"avgTipAmount":2.3103201487727123,"avgTotalAmount":18.006578271170497,"numberOfTrips":229612},{"day":"Sunday","weather":"sunny","season":"spring","time":"night","area":"not manhattan","avgDuration":1356.4088944245,"avgDistance":11.039939189684226,"avgFareAmount":32.86224412044839,"avgTipAmount":5.722588468019635,"avgTotalAmount":44.337501404254276,"numberOfTrips":40947},{"day":"Sunday","weather":"sunny","season":"summer","time":"day","area":"manhattan","avgDuration":773.3605232553833,"avgDistance":2.868241513025829,"avgFareAmount":12.179078636454545,"avgTipAmount":2.2511319545781143,"avgTotalAmount":18.072784090488216,"numberOfTrips":540004},{"day":"Sunday","weather":"sunny","season":"summer","time":"day","area":"not manhattan","avgDuration":1770.5952811824434,"avgDistance":10.984435923270304,"avgFareAmount":33.81420546029013,"avgTipAmount":5.615540208747028,"avgTotalAmount":45.505921216093284,"numberOfTrips":102229},{"day":"Sunday","weather":"sunny","season":"summer","time":"night","area":"manhattan","avgDuration":736.8561080544409,"avgDistance":3.0053479088238944,"avgFareAmount":12.02341877301121,"avgTipAmount":2.3007196458859056,"avgTotalAmount":18.224746990443883,"numberOfTrips":241730},{"day":"Sunday","weather":"sunny","season":"summer","time":"night","area":"not manhattan","avgDuration":1452.279665238617,"avgDistance":10.78519328484607,"avgFareAmount":32.57237122646209,"avgTipAmount":5.391930855833416,"avgTotalAmount":43.491437680581846,"numberOfTrips":40148},{"day":"Sunday","weather":"sunny","season":"winter","time":"day","area":"manhattan","avgDuration":721.5655239247494,"avgDistance":2.5653878344549823,"avgFareAmount":11.487496766387947,"avgTipAmount":2.22455063736981,"avgTotalAmount":17.281276649938114,"numberOfTrips":502534},{"day":"Sunday","weather":"sunny","season":"winter","time":"day","area":"not manhattan","avgDuration":1556.3174361349454,"avgDistance":10.46784674824493,"avgFareAmount":33.05574029836193,"avgTipAmount":5.548873951833073,"avgTotalAmount":44.71023157176287,"numberOfTrips":82048},{"day":"Sunday","weather":"sunny","season":"winter","time":"night","area":"manhattan","avgDuration":695.1361485877902,"avgDistance":2.846170963184891,"avgFareAmount":11.649556616385237,"avgTipAmount":2.3451405572990245,"avgTotalAmount":17.917251002626266,"numberOfTrips":210946},{"day":"Sunday","weather":"sunny","season":"winter","time":"night","area":"not manhattan","avgDuration":1245.5319059749138,"avgDistance":10.287584238867572,"avgFareAmount":31.75906652049141,"avgTipAmount":5.333101280108342,"avgTotalAmount":42.640611356527906,"numberOfTrips":31013}]